ossos/__init__.py
ossos/astrom.py
ossos/auth.py
ossos/cadc.py
ossos/cameras.py
ossos/caom2.py
ossos/coding.py
ossos/coord.py
ossos/daophot.py
ossos/ephem_target.py
ossos/figures.py
ossos/junk_keywords.py
ossos/kbo.py
ossos/match.py
ossos/mop_file.py
ossos/mopheader.py
ossos/mpc.py
ossos/mpc_time.py
ossos/naming.py
ossos/orbfit.py
ossos/parameters.py
ossos/plant.py
ossos/ssos.py
ossos/storage.py
ossos/util.py
ossos/version.py
ossos/vospace.py
ossos/wcs.py
ossos/downloads/__init__.py
ossos/downloads/async_download.py
ossos/downloads/core.py
ossos/downloads/cutouts/__init__.py
ossos/downloads/cutouts/calculator.py
ossos/downloads/cutouts/downloader.py
ossos/downloads/cutouts/focus.py
ossos/downloads/cutouts/grid.py
ossos/downloads/cutouts/source.py
ossos/fitsviewer/__init__.py
ossos/fitsviewer/baseviewer.py
ossos/fitsviewer/colormap.py
ossos/fitsviewer/displayable.py
ossos/fitsviewer/exceptions.py
ossos/fitsviewer/interaction.py
ossos/fitsviewer/singletviewer.py
ossos/fitsviewer/tripletviewer.py
ossos/fitsviewer/util.py
ossos/gui/SSOLS.py
ossos/gui/__init__.py
ossos/gui/app.py
ossos/gui/autoplay.py
ossos/gui/config.json
ossos/gui/config.py
ossos/gui/context.py
ossos/gui/controllers.py
ossos/gui/env.json
ossos/gui/errorhandling.py
ossos/gui/events.py
ossos/gui/logger.py
ossos/gui/progress.py
ossos/gui/sync.py
ossos/gui/tasks.py
ossos/gui/models/__init__.py
ossos/gui/models/collections.py
ossos/gui/models/exceptions.py
ossos/gui/models/imagemanager.py
ossos/gui/models/transactions.py
ossos/gui/models/validation.py
ossos/gui/models/workload.py
ossos/gui/views/__init__.py
ossos/gui/views/appview.py
ossos/gui/views/dialogs.py
ossos/gui/views/errorhandling.py
ossos/gui/views/imageview.py
ossos/gui/views/keybinds.py
ossos/gui/views/listctrls.py
ossos/gui/views/loading.py
ossos/gui/views/mainframe.py
ossos/gui/views/menu.py
ossos/gui/views/navigation.py
ossos/gui/views/validation.py
ossos/pipeline/__init__.py
ossos/pipeline/align.py
ossos/pipeline/astrom_mag_check.py
ossos-3.1.12.dist-info/METADATA
ossos-3.1.12.dist-info/WHEEL
ossos-3.1.12.dist-info/entry_points.txt
ossos-3.1.12.dist-info/top_level.txt
ossos-3.1.12.dist-info/RECORD
